[
  {
    "data": "13/09/2025",
    "partita": "Preston North End vs Middlesbrough",
    "risultato": "",
    "previsione": "1 - 1",
    "p1": "31,57%",
    "pX": "34,12%",
    "p2": "34,31%",
    "pUnder": "56,65%",
    "pOver": "43,35%",
    "pGG": "61,04%",
    "pNG": "38,96%"
  },
  {
    "data": "13/09/2025",
    "partita": "Southampton vs Portsmouth",
    "risultato": "",
    "previsione": "1 - 1",
    "p1": "40,22%",
    "pX": "33,16%",
    "p2": "26,63%",
    "pUnder": "46,75%",
    "pOver": "53,25%",
    "pGG": "69,08%",
    "pNG": "30,92%"
  },
  {
    "data": "13/09/2025",
    "partita": "Swansea City vs Hull City",
    "risultato": "",
    "previsione": "1 - 1",
    "p1": "42,01%",
    "pX": "31,37%",
    "p2": "26,62%",
    "pUnder": "69,84%",
    "pOver": "30,16%",
    "pGG": "47,86%",
    "pNG": "52,14%"
  },
  {
    "data": "13/09/2025",
    "partita": "Coventry City vs Norwich City",
    "risultato": "",
    "previsione": "2 - 1",
    "p1": "51,49%",
    "pX": "22,70%",
    "p2": "25,81%",
    "pUnder": "39,32%",
    "pOver": "60,68%",
    "pGG": "63,38%",
    "pNG": "36,62%"
  },
  {
    "data": "13/09/2025",
    "partita": "Watford vs Blackburn Rovers",
    "risultato": "",
    "previsione": "1 - 1",
    "p1": "37,61%",
    "pX": "25,88%",
    "p2": "36,51%",
    "pUnder": "58,85%",
    "pOver": "41,15%",
    "pGG": "52,80%",
    "pNG": "47,20%"
  },
  {
    "data": "13/09/2025",
    "partita": "Stoke City vs Birmingham City",
    "risultato": "",
    "previsione": "1 - 1",
    "p1": "33,42%",
    "pX": "32,18%",
    "p2": "34,39%",
    "pUnder": "66,17%",
    "pOver": "33,83%",
    "pGG": "50,63%",
    "pNG": "49,37%"
  },
  {
    "data": "13/09/2025",
    "partita": "Oxford United vs Leicester City",
    "risultato": "",
    "previsione": "1 - 1",
    "p1": "29,54%",
    "pX": "29,27%",
    "p2": "41,19%",
    "pUnder": "67,14%",
    "pOver": "32,86%",
    "pGG": "54,51%",
    "pNG": "45,49%"
  },
  {
    "data": "13/09/2025",
    "partita": "Wrexham vs Queens Park Rangers",
    "risultato": "",
    "previsione": "2 - 1",
    "p1": "45,78%",
    "pX": "26,21%",
    "p2": "28,01%",
    "pUnder": "35,78%",
    "pOver": "64,22%",
    "pGG": "71,99%",
    "pNG": "28,01%"
  },
  {
    "data": "13/09/2025",
    "partita": "West Bromwich Albion vs Derby County",
    "risultato": "",
    "previsione": "2 - 1",
    "p1": "49,51%",
    "pX": "32,42%",
    "p2": "18,08%",
    "pUnder": "52,69%",
    "pOver": "47,31%",
    "pGG": "60,49%",
    "pNG": "39,51%"
  },
  {
    "data": "13/09/2025",
    "partita": "Charlton Athletic vs Millwall",
    "risultato": "",
    "previsione": "1 - 1",
    "p1": "35,36%",
    "pX": "26,36%",
    "p2": "38,28%",
    "pUnder": "71,99%",
    "pOver": "28,01%",
    "pGG": "45,78%",
    "pNG": "54,22%"
  },
  {
    "data": "13/09/2025",
    "partita": "Ipswich Town vs Sheffield United",
    "risultato": "",
    "previsione": "1 - 1",
    "p1": "28,34%",
    "pX": "26,50%",
    "p2": "45,16%",
    "pUnder": "66,68%",
    "pOver": "33,32%",
    "pGG": "47,06%",
    "pNG": "52,94%"
  },
  {
    "data": "13/09/2025",
    "partita": "Sheffield Wednesday vs Bristol City",
    "risultato": "",
    "previsione": "1 - 1",
    "p1": "27,23%",
    "pX": "37,97%",
    "p2": "34,80%",
    "pUnder": "56,35%",
    "pOver": "43,65%",
    "pGG": "58,51%",
    "pNG": "41,49%"
  }
]