[
  {
    "data": "2025-08-23T15:00:00Z",
    "partita": "Moreirense FC vs Vitória SC",
    "risultato": "2-0",
    "previsione": "1 - 1",
    "p1": "33,80%",
    "pX": "35,82%",
    "p2": "30,38%",
    "pUnder": "56,37%",
    "pOver": "43,63%",
    "pGG": "55,68%",
    "pNG": "44,32%"
  },
  {
    "data": "2025-08-23T17:00:00Z",
    "partita": "CD Nacional vs Sporting Clube de Portugal",
    "risultato": "1-4",
    "previsione": "1 - 3",
    "p1": "11,44%",
    "pX": "19,86%",
    "p2": "68,70%",
    "pUnder": "35,41%",
    "pOver": "64,59%",
    "pGG": "52,95%",
    "pNG": "47,05%"
  },
  {
    "data": "2025-08-23T19:30:00Z",
    "partita": "FC Arouca vs Rio Ave FC",
    "risultato": "3-3",
    "previsione": "2 - 1",
    "p1": "40,92%",
    "pX": "37,32%",
    "p2": "21,76%",
    "pUnder": "45,70%",
    "pOver": "54,30%",
    "pGG": "62,04%",
    "pNG": "37,96%"
  },
  {
    "data": "2025-08-23T19:30:00Z",
    "partita": "Sport Lisboa e Benfica vs CD Tondela",
    "risultato": "3-0",
    "previsione": "3 - 0",
    "p1": "82,78%",
    "pX": "16,05%",
    "p2": "1,17%",
    "pUnder": "20,93%",
    "pOver": "79,07%",
    "pGG": "38,21%",
    "pNG": "61,79%"
  },
  {
    "data": "2025-08-24T14:30:00Z",
    "partita": "FC Famalicão vs Gil Vicente FC",
    "risultato": "0-0",
    "previsione": "1 - 1",
    "p1": "39,28%",
    "pX": "37,19%",
    "p2": "23,53%",
    "pUnder": "61,85%",
    "pOver": "38,15%",
    "pGG": "50,89%",
    "pNG": "49,11%"
  },
  {
    "data": "2025-08-24T17:00:00Z",
    "partita": "FC Porto vs Casa Pia AC",
    "risultato": "4-0",
    "previsione": "2 - 1",
    "p1": "65,27%",
    "pX": "18,49%",
    "p2": "16,23%",
    "pUnder": "41,58%",
    "pOver": "58,42%",
    "pGG": "50,21%",
    "pNG": "49,79%"
  },
  {
    "data": "2025-08-24T19:30:00Z",
    "partita": "Sporting Clube de Braga vs AVS",
    "risultato": "2-2",
    "previsione": "2 - 1",
    "p1": "59,11%",
    "pX": "32,88%",
    "p2": "8,01%",
    "pUnder": "43,63%",
    "pOver": "56,37%",
    "pGG": "59,79%",
    "pNG": "40,21%"
  },
  {
    "data": "2025-08-25T19:15:00Z",
    "partita": "CF Estrela da Amadora vs FC Alverca",
    "risultato": "2-2",
    "previsione": "1 - 1",
    "p1": "23,38%",
    "pX": "34,41%",
    "p2": "42,21%",
    "pUnder": "61,47%",
    "pOver": "38,53%",
    "pGG": "46,18%",
    "pNG": "53,82%"
  },
  {
    "data": "2025-09-06T19:30:00Z",
    "partita": "GD Estoril Praia vs CD Santa Clara",
    "risultato": "",
    "previsione": "1 - 1",
    "p1": "30,83%",
    "pX": "32,54%",
    "p2": "36,63%",
    "pUnder": "55,00%",
    "pOver": "45,00%",
    "pGG": "56,45%",
    "pNG": "43,55%"
  }
]