[
  {
    "team": "Jagiellonia Bialystok",
    "totale": {
      "PG": 3,
      "V": 2,
      "P": 0,
      "S": 1,
      "GF": 8,
      "GS": 8,
      "OV": 3,
      "UN": 0,
      "GG": 2,
      "NG": 1
    },
    "casa": {
      "PG": 3,
      "V": 2,
      "P": 0,
      "S": 1,
      "GF": 8,
      "GS": 8,
      "OV": 3,
      "UN": 0,
      "GG": 2,
      "NG": 1
    },
    "trasferta": {
      "PG": 0,
      "V": 0,
      "P": 0,
      "S": 0,
      "GF": 0,
      "GS": 0,
      "OV": 0,
      "UN": 0,
      "GG": 0,
      "NG": 0
    },
    "ultime5": {
      "PG": 3,
      "V": 2,
      "P": 0,
      "S": 1,
      "GF": 8,
      "GS": 8,
      "OV": 3,
      "UN": 0,
      "GG": 2,
      "NG": 1
    },
    "ultime5_casa": {
      "PG": 3,
      "V": 2,
      "P": 0,
      "S": 1,
      "GF": 8,
      "GS": 8,
      "OV": 3,
      "UN": 0,
      "GG": 2,
      "NG": 1
    },
    "ultime5_trasferta": {
      "PG": 0,
      "V": 0,
      "P": 0,
      "S": 0,
      "GF": 0,
      "GS": 0,
      "OV": 0,
      "UN": 0,
      "GG": 0,
      "NG": 0
    }
  },
  {
    "team": "Nieciecza",
    "totale": {
      "PG": 4,
      "V": 2,
      "P": 1,
      "S": 1,
      "GF": 6,
      "GS": 3,
      "OV": 1,
      "UN": 3,
      "GG": 1,
      "NG": 3
    },
    "casa": {
      "PG": 1,
      "V": 0,
      "P": 1,
      "S": 0,
      "GF": 1,
      "GS": 1,
      "OV": 0,
      "UN": 1,
      "GG": 1,
      "NG": 0
    },
    "trasferta": {
      "PG": 3,
      "V": 2,
      "P": 0,
      "S": 1,
      "GF": 5,
      "GS": 2,
      "OV": 1,
      "UN": 2,
      "GG": 0,
      "NG": 3
    },
    "ultime5": {
      "PG": 4,
      "V": 2,
      "P": 1,
      "S": 1,
      "GF": 6,
      "GS": 3,
      "OV": 1,
      "UN": 3,
      "GG": 1,
      "NG": 3
    },
    "ultime5_casa": {
      "PG": 1,
      "V": 0,
      "P": 1,
      "S": 0,
      "GF": 1,
      "GS": 1,
      "OV": 0,
      "UN": 1,
      "GG": 1,
      "NG": 0
    },
    "ultime5_trasferta": {
      "PG": 3,
      "V": 2,
      "P": 0,
      "S": 1,
      "GF": 5,
      "GS": 2,
      "OV": 1,
      "UN": 2,
      "GG": 0,
      "NG": 3
    }
  },
  {
    "team": "Lech Poznan",
    "totale": {
      "PG": 3,
      "V": 2,
      "P": 0,
      "S": 1,
      "GF": 7,
      "GS": 8,
      "OV": 3,
      "UN": 0,
      "GG": 3,
      "NG": 0
    },
    "casa": {
      "PG": 2,
      "V": 1,
      "P": 0,
      "S": 1,
      "GF": 3,
      "GS": 5,
      "OV": 2,
      "UN": 0,
      "GG": 2,
      "NG": 0
    },
    "trasferta": {
      "PG": 1,
      "V": 1,
      "P": 0,
      "S": 0,
      "GF": 4,
      "GS": 3,
      "OV": 1,
      "UN": 0,
      "GG": 1,
      "NG": 0
    },
    "ultime5": {
      "PG": 3,
      "V": 2,
      "P": 0,
      "S": 1,
      "GF": 7,
      "GS": 8,
      "OV": 3,
      "UN": 0,
      "GG": 3,
      "NG": 0
    },
    "ultime5_casa": {
      "PG": 2,
      "V": 1,
      "P": 0,
      "S": 1,
      "GF": 3,
      "GS": 5,
      "OV": 2,
      "UN": 0,
      "GG": 2,
      "NG": 0
    },
    "ultime5_trasferta": {
      "PG": 1,
      "V": 1,
      "P": 0,
      "S": 0,
      "GF": 4,
      "GS": 3,
      "OV": 1,
      "UN": 0,
      "GG": 1,
      "NG": 0
    }
  },
  {
    "team": "Cracovia",
    "totale": {
      "PG": 5,
      "V": 3,
      "P": 1,
      "S": 1,
      "GF": 11,
      "GS": 8,
      "OV": 3,
      "UN": 2,
      "GG": 3,
      "NG": 2
    },
    "casa": {
      "PG": 3,
      "V": 2,
      "P": 1,
      "S": 0,
      "GF": 5,
      "GS": 2,
      "OV": 1,
      "UN": 2,
      "GG": 1,
      "NG": 2
    },
    "trasferta": {
      "PG": 2,
      "V": 1,
      "P": 0,
      "S": 1,
      "GF": 6,
      "GS": 6,
      "OV": 2,
      "UN": 0,
      "GG": 2,
      "NG": 0
    },
    "ultime5": {
      "PG": 5,
      "V": 3,
      "P": 1,
      "S": 1,
      "GF": 11,
      "GS": 8,
      "OV": 3,
      "UN": 2,
      "GG": 3,
      "NG": 2
    },
    "ultime5_casa": {
      "PG": 3,
      "V": 2,
      "P": 1,
      "S": 0,
      "GF": 5,
      "GS": 2,
      "OV": 1,
      "UN": 2,
      "GG": 1,
      "NG": 2
    },
    "ultime5_trasferta": {
      "PG": 2,
      "V": 1,
      "P": 0,
      "S": 1,
      "GF": 6,
      "GS": 6,
      "OV": 2,
      "UN": 0,
      "GG": 2,
      "NG": 0
    }
  },
  {
    "team": "Widzew Lodz",
    "totale": {
      "PG": 5,
      "V": 2,
      "P": 1,
      "S": 2,
      "GF": 7,
      "GS": 5,
      "OV": 2,
      "UN": 3,
      "GG": 2,
      "NG": 3
    },
    "casa": {
      "PG": 3,
      "V": 2,
      "P": 1,
      "S": 0,
      "GF": 5,
      "GS": 1,
      "OV": 1,
      "UN": 2,
      "GG": 1,
      "NG": 2
    },
    "trasferta": {
      "PG": 2,
      "V": 0,
      "P": 0,
      "S": 2,
      "GF": 2,
      "GS": 4,
      "OV": 1,
      "UN": 1,
      "GG": 1,
      "NG": 1
    },
    "ultime5": {
      "PG": 5,
      "V": 2,
      "P": 1,
      "S": 2,
      "GF": 7,
      "GS": 5,
      "OV": 2,
      "UN": 3,
      "GG": 2,
      "NG": 3
    },
    "ultime5_casa": {
      "PG": 3,
      "V": 2,
      "P": 1,
      "S": 0,
      "GF": 5,
      "GS": 1,
      "OV": 1,
      "UN": 2,
      "GG": 1,
      "NG": 2
    },
    "ultime5_trasferta": {
      "PG": 2,
      "V": 0,
      "P": 0,
      "S": 2,
      "GF": 2,
      "GS": 4,
      "OV": 1,
      "UN": 1,
      "GG": 1,
      "NG": 1
    }
  },
  {
    "team": "Zaglebie Lubin",
    "totale": {
      "PG": 4,
      "V": 1,
      "P": 2,
      "S": 1,
      "GF": 9,
      "GS": 6,
      "OV": 2,
      "UN": 2,
      "GG": 3,
      "NG": 1
    },
    "casa": {
      "PG": 2,
      "V": 1,
      "P": 1,
      "S": 0,
      "GF": 7,
      "GS": 3,
      "OV": 1,
      "UN": 1,
      "GG": 2,
      "NG": 0
    },
    "trasferta": {
      "PG": 2,
      "V": 0,
      "P": 1,
      "S": 1,
      "GF": 2,
      "GS": 3,
      "OV": 1,
      "UN": 1,
      "GG": 1,
      "NG": 1
    },
    "ultime5": {
      "PG": 4,
      "V": 1,
      "P": 2,
      "S": 1,
      "GF": 9,
      "GS": 6,
      "OV": 2,
      "UN": 2,
      "GG": 3,
      "NG": 1
    },
    "ultime5_casa": {
      "PG": 2,
      "V": 1,
      "P": 1,
      "S": 0,
      "GF": 7,
      "GS": 3,
      "OV": 1,
      "UN": 1,
      "GG": 2,
      "NG": 0
    },
    "ultime5_trasferta": {
      "PG": 2,
      "V": 0,
      "P": 1,
      "S": 1,
      "GF": 2,
      "GS": 3,
      "OV": 1,
      "UN": 1,
      "GG": 1,
      "NG": 1
    }
  },
  {
    "team": "Wisla Plock",
    "totale": {
      "PG": 4,
      "V": 3,
      "P": 1,
      "S": 0,
      "GF": 7,
      "GS": 2,
      "OV": 1,
      "UN": 3,
      "GG": 2,
      "NG": 2
    },
    "casa": {
      "PG": 2,
      "V": 2,
      "P": 0,
      "S": 0,
      "GF": 4,
      "GS": 0,
      "OV": 0,
      "UN": 2,
      "GG": 0,
      "NG": 2
    },
    "trasferta": {
      "PG": 2,
      "V": 1,
      "P": 1,
      "S": 0,
      "GF": 3,
      "GS": 2,
      "OV": 1,
      "UN": 1,
      "GG": 2,
      "NG": 0
    },
    "ultime5": {
      "PG": 4,
      "V": 3,
      "P": 1,
      "S": 0,
      "GF": 7,
      "GS": 2,
      "OV": 1,
      "UN": 3,
      "GG": 2,
      "NG": 2
    },
    "ultime5_casa": {
      "PG": 2,
      "V": 2,
      "P": 0,
      "S": 0,
      "GF": 4,
      "GS": 0,
      "OV": 0,
      "UN": 2,
      "GG": 0,
      "NG": 2
    },
    "ultime5_trasferta": {
      "PG": 2,
      "V": 1,
      "P": 1,
      "S": 0,
      "GF": 3,
      "GS": 2,
      "OV": 1,
      "UN": 1,
      "GG": 2,
      "NG": 0
    }
  },
  {
    "team": "Korona Kielce",
    "totale": {
      "PG": 4,
      "V": 1,
      "P": 1,
      "S": 2,
      "GF": 4,
      "GS": 5,
      "OV": 1,
      "UN": 3,
      "GG": 1,
      "NG": 3
    },
    "casa": {
      "PG": 2,
      "V": 1,
      "P": 0,
      "S": 1,
      "GF": 3,
      "GS": 2,
      "OV": 1,
      "UN": 1,
      "GG": 0,
      "NG": 2
    },
    "trasferta": {
      "PG": 2,
      "V": 0,
      "P": 1,
      "S": 1,
      "GF": 1,
      "GS": 3,
      "OV": 0,
      "UN": 2,
      "GG": 1,
      "NG": 1
    },
    "ultime5": {
      "PG": 4,
      "V": 1,
      "P": 1,
      "S": 2,
      "GF": 4,
      "GS": 5,
      "OV": 1,
      "UN": 3,
      "GG": 1,
      "NG": 3
    },
    "ultime5_casa": {
      "PG": 2,
      "V": 1,
      "P": 0,
      "S": 1,
      "GF": 3,
      "GS": 2,
      "OV": 1,
      "UN": 1,
      "GG": 0,
      "NG": 2
    },
    "ultime5_trasferta": {
      "PG": 2,
      "V": 0,
      "P": 1,
      "S": 1,
      "GF": 1,
      "GS": 3,
      "OV": 0,
      "UN": 2,
      "GG": 1,
      "NG": 1
    }
  },
  {
    "team": "GKS Katowice",
    "totale": {
      "PG": 4,
      "V": 0,
      "P": 1,
      "S": 3,
      "GF": 3,
      "GS": 9,
      "OV": 3,
      "UN": 1,
      "GG": 2,
      "NG": 2
    },
    "casa": {
      "PG": 2,
      "V": 0,
      "P": 1,
      "S": 1,
      "GF": 2,
      "GS": 3,
      "OV": 1,
      "UN": 1,
      "GG": 1,
      "NG": 1
    },
    "trasferta": {
      "PG": 2,
      "V": 0,
      "P": 0,
      "S": 2,
      "GF": 1,
      "GS": 6,
      "OV": 2,
      "UN": 0,
      "GG": 1,
      "NG": 1
    },
    "ultime5": {
      "PG": 4,
      "V": 0,
      "P": 1,
      "S": 3,
      "GF": 3,
      "GS": 9,
      "OV": 3,
      "UN": 1,
      "GG": 2,
      "NG": 2
    },
    "ultime5_casa": {
      "PG": 2,
      "V": 0,
      "P": 1,
      "S": 1,
      "GF": 2,
      "GS": 3,
      "OV": 1,
      "UN": 1,
      "GG": 1,
      "NG": 1
    },
    "ultime5_trasferta": {
      "PG": 2,
      "V": 0,
      "P": 0,
      "S": 2,
      "GF": 1,
      "GS": 6,
      "OV": 2,
      "UN": 0,
      "GG": 1,
      "NG": 1
    }
  },
  {
    "team": "Rakow Czestochowa",
    "totale": {
      "PG": 3,
      "V": 1,
      "P": 0,
      "S": 2,
      "GF": 3,
      "GS": 5,
      "OV": 2,
      "UN": 1,
      "GG": 2,
      "NG": 1
    },
    "casa": {
      "PG": 1,
      "V": 0,
      "P": 0,
      "S": 1,
      "GF": 1,
      "GS": 2,
      "OV": 1,
      "UN": 0,
      "GG": 1,
      "NG": 0
    },
    "trasferta": {
      "PG": 2,
      "V": 1,
      "P": 0,
      "S": 1,
      "GF": 2,
      "GS": 3,
      "OV": 1,
      "UN": 1,
      "GG": 1,
      "NG": 1
    },
    "ultime5": {
      "PG": 3,
      "V": 1,
      "P": 0,
      "S": 2,
      "GF": 3,
      "GS": 5,
      "OV": 2,
      "UN": 1,
      "GG": 2,
      "NG": 1
    },
    "ultime5_casa": {
      "PG": 1,
      "V": 0,
      "P": 0,
      "S": 1,
      "GF": 1,
      "GS": 2,
      "OV": 1,
      "UN": 0,
      "GG": 1,
      "NG": 0
    },
    "ultime5_trasferta": {
      "PG": 2,
      "V": 1,
      "P": 0,
      "S": 1,
      "GF": 2,
      "GS": 3,
      "OV": 1,
      "UN": 1,
      "GG": 1,
      "NG": 1
    }
  },
  {
    "team": "Gornik Zabrze",
    "totale": {
      "PG": 4,
      "V": 2,
      "P": 0,
      "S": 2,
      "GF": 4,
      "GS": 4,
      "OV": 2,
      "UN": 2,
      "GG": 2,
      "NG": 2
    },
    "casa": {
      "PG": 2,
      "V": 1,
      "P": 0,
      "S": 1,
      "GF": 2,
      "GS": 2,
      "OV": 1,
      "UN": 1,
      "GG": 1,
      "NG": 1
    },
    "trasferta": {
      "PG": 2,
      "V": 1,
      "P": 0,
      "S": 1,
      "GF": 2,
      "GS": 2,
      "OV": 1,
      "UN": 1,
      "GG": 1,
      "NG": 1
    },
    "ultime5": {
      "PG": 4,
      "V": 2,
      "P": 0,
      "S": 2,
      "GF": 4,
      "GS": 4,
      "OV": 2,
      "UN": 2,
      "GG": 2,
      "NG": 2
    },
    "ultime5_casa": {
      "PG": 2,
      "V": 1,
      "P": 0,
      "S": 1,
      "GF": 2,
      "GS": 2,
      "OV": 1,
      "UN": 1,
      "GG": 1,
      "NG": 1
    },
    "ultime5_trasferta": {
      "PG": 2,
      "V": 1,
      "P": 0,
      "S": 1,
      "GF": 2,
      "GS": 2,
      "OV": 1,
      "UN": 1,
      "GG": 1,
      "NG": 1
    }
  },
  {
    "team": "Lechia Gdansk",
    "totale": {
      "PG": 5,
      "V": 0,
      "P": 2,
      "S": 3,
      "GF": 11,
      "GS": 17,
      "OV": 5,
      "UN": 0,
      "GG": 5,
      "NG": 0
    },
    "casa": {
      "PG": 2,
      "V": 0,
      "P": 1,
      "S": 1,
      "GF": 6,
      "GS": 7,
      "OV": 2,
      "UN": 0,
      "GG": 2,
      "NG": 0
    },
    "trasferta": {
      "PG": 3,
      "V": 0,
      "P": 1,
      "S": 2,
      "GF": 5,
      "GS": 10,
      "OV": 3,
      "UN": 0,
      "GG": 3,
      "NG": 0
    },
    "ultime5": {
      "PG": 5,
      "V": 0,
      "P": 2,
      "S": 3,
      "GF": 11,
      "GS": 17,
      "OV": 5,
      "UN": 0,
      "GG": 5,
      "NG": 0
    },
    "ultime5_casa": {
      "PG": 2,
      "V": 0,
      "P": 1,
      "S": 1,
      "GF": 6,
      "GS": 7,
      "OV": 2,
      "UN": 0,
      "GG": 2,
      "NG": 0
    },
    "ultime5_trasferta": {
      "PG": 3,
      "V": 0,
      "P": 1,
      "S": 2,
      "GF": 5,
      "GS": 10,
      "OV": 3,
      "UN": 0,
      "GG": 3,
      "NG": 0
    }
  },
  {
    "team": "Motor Lublin",
    "totale": {
      "PG": 3,
      "V": 1,
      "P": 1,
      "S": 1,
      "GF": 5,
      "GS": 7,
      "OV": 2,
      "UN": 1,
      "GG": 2,
      "NG": 1
    },
    "casa": {
      "PG": 1,
      "V": 1,
      "P": 0,
      "S": 0,
      "GF": 1,
      "GS": 0,
      "OV": 0,
      "UN": 1,
      "GG": 0,
      "NG": 1
    },
    "trasferta": {
      "PG": 2,
      "V": 0,
      "P": 1,
      "S": 1,
      "GF": 4,
      "GS": 7,
      "OV": 2,
      "UN": 0,
      "GG": 2,
      "NG": 0
    },
    "ultime5": {
      "PG": 3,
      "V": 1,
      "P": 1,
      "S": 1,
      "GF": 5,
      "GS": 7,
      "OV": 2,
      "UN": 1,
      "GG": 2,
      "NG": 1
    },
    "ultime5_casa": {
      "PG": 1,
      "V": 1,
      "P": 0,
      "S": 0,
      "GF": 1,
      "GS": 0,
      "OV": 0,
      "UN": 1,
      "GG": 0,
      "NG": 1
    },
    "ultime5_trasferta": {
      "PG": 2,
      "V": 0,
      "P": 1,
      "S": 1,
      "GF": 4,
      "GS": 7,
      "OV": 2,
      "UN": 0,
      "GG": 2,
      "NG": 0
    }
  },
  {
    "team": "Arka Gdynia",
    "totale": {
      "PG": 4,
      "V": 1,
      "P": 2,
      "S": 1,
      "GF": 3,
      "GS": 3,
      "OV": 1,
      "UN": 3,
      "GG": 2,
      "NG": 2
    },
    "casa": {
      "PG": 2,
      "V": 1,
      "P": 1,
      "S": 0,
      "GF": 3,
      "GS": 2,
      "OV": 1,
      "UN": 1,
      "GG": 2,
      "NG": 0
    },
    "trasferta": {
      "PG": 2,
      "V": 0,
      "P": 1,
      "S": 1,
      "GF": 0,
      "GS": 1,
      "OV": 0,
      "UN": 2,
      "GG": 0,
      "NG": 2
    },
    "ultime5": {
      "PG": 4,
      "V": 1,
      "P": 2,
      "S": 1,
      "GF": 3,
      "GS": 3,
      "OV": 1,
      "UN": 3,
      "GG": 2,
      "NG": 2
    },
    "ultime5_casa": {
      "PG": 2,
      "V": 1,
      "P": 1,
      "S": 0,
      "GF": 3,
      "GS": 2,
      "OV": 1,
      "UN": 1,
      "GG": 2,
      "NG": 0
    },
    "ultime5_trasferta": {
      "PG": 2,
      "V": 0,
      "P": 1,
      "S": 1,
      "GF": 0,
      "GS": 1,
      "OV": 0,
      "UN": 2,
      "GG": 0,
      "NG": 2
    }
  },
  {
    "team": "Legia Warsaw",
    "totale": {
      "PG": 3,
      "V": 2,
      "P": 1,
      "S": 0,
      "GF": 5,
      "GS": 1,
      "OV": 1,
      "UN": 2,
      "GG": 1,
      "NG": 2
    },
    "casa": {
      "PG": 2,
      "V": 1,
      "P": 1,
      "S": 0,
      "GF": 3,
      "GS": 1,
      "OV": 1,
      "UN": 1,
      "GG": 1,
      "NG": 1
    },
    "trasferta": {
      "PG": 1,
      "V": 1,
      "P": 0,
      "S": 0,
      "GF": 2,
      "GS": 0,
      "OV": 0,
      "UN": 1,
      "GG": 0,
      "NG": 1
    },
    "ultime5": {
      "PG": 3,
      "V": 2,
      "P": 1,
      "S": 0,
      "GF": 5,
      "GS": 1,
      "OV": 1,
      "UN": 2,
      "GG": 1,
      "NG": 2
    },
    "ultime5_casa": {
      "PG": 2,
      "V": 1,
      "P": 1,
      "S": 0,
      "GF": 3,
      "GS": 1,
      "OV": 1,
      "UN": 1,
      "GG": 1,
      "NG": 1
    },
    "ultime5_trasferta": {
      "PG": 1,
      "V": 1,
      "P": 0,
      "S": 0,
      "GF": 2,
      "GS": 0,
      "OV": 0,
      "UN": 1,
      "GG": 0,
      "NG": 1
    }
  },
  {
    "team": "Piast Gliwice",
    "totale": {
      "PG": 2,
      "V": 0,
      "P": 0,
      "S": 2,
      "GF": 0,
      "GS": 3,
      "OV": 0,
      "UN": 2,
      "GG": 0,
      "NG": 2
    },
    "casa": {
      "PG": 1,
      "V": 0,
      "P": 0,
      "S": 1,
      "GF": 0,
      "GS": 1,
      "OV": 0,
      "UN": 1,
      "GG": 0,
      "NG": 1
    },
    "trasferta": {
      "PG": 1,
      "V": 0,
      "P": 0,
      "S": 1,
      "GF": 0,
      "GS": 2,
      "OV": 0,
      "UN": 1,
      "GG": 0,
      "NG": 1
    },
    "ultime5": {
      "PG": 2,
      "V": 0,
      "P": 0,
      "S": 2,
      "GF": 0,
      "GS": 3,
      "OV": 0,
      "UN": 2,
      "GG": 0,
      "NG": 2
    },
    "ultime5_casa": {
      "PG": 1,
      "V": 0,
      "P": 0,
      "S": 1,
      "GF": 0,
      "GS": 1,
      "OV": 0,
      "UN": 1,
      "GG": 0,
      "NG": 1
    },
    "ultime5_trasferta": {
      "PG": 1,
      "V": 0,
      "P": 0,
      "S": 1,
      "GF": 0,
      "GS": 2,
      "OV": 0,
      "UN": 1,
      "GG": 0,
      "NG": 1
    }
  },
  {
    "team": "Radomiak Radom",
    "totale": {
      "PG": 4,
      "V": 2,
      "P": 1,
      "S": 1,
      "GF": 9,
      "GS": 6,
      "OV": 3,
      "UN": 1,
      "GG": 3,
      "NG": 1
    },
    "casa": {
      "PG": 2,
      "V": 2,
      "P": 0,
      "S": 0,
      "GF": 8,
      "GS": 2,
      "OV": 2,
      "UN": 0,
      "GG": 2,
      "NG": 0
    },
    "trasferta": {
      "PG": 2,
      "V": 0,
      "P": 1,
      "S": 1,
      "GF": 1,
      "GS": 4,
      "OV": 1,
      "UN": 1,
      "GG": 1,
      "NG": 1
    },
    "ultime5": {
      "PG": 4,
      "V": 2,
      "P": 1,
      "S": 1,
      "GF": 9,
      "GS": 6,
      "OV": 3,
      "UN": 1,
      "GG": 3,
      "NG": 1
    },
    "ultime5_casa": {
      "PG": 2,
      "V": 2,
      "P": 0,
      "S": 0,
      "GF": 8,
      "GS": 2,
      "OV": 2,
      "UN": 0,
      "GG": 2,
      "NG": 0
    },
    "ultime5_trasferta": {
      "PG": 2,
      "V": 0,
      "P": 1,
      "S": 1,
      "GF": 1,
      "GS": 4,
      "OV": 1,
      "UN": 1,
      "GG": 1,
      "NG": 1
    }
  },
  {
    "team": "Pogon Szczecin",
    "totale": {
      "PG": 4,
      "V": 1,
      "P": 1,
      "S": 2,
      "GF": 7,
      "GS": 9,
      "OV": 3,
      "UN": 1,
      "GG": 4,
      "NG": 0
    },
    "casa": {
      "PG": 1,
      "V": 1,
      "P": 0,
      "S": 0,
      "GF": 4,
      "GS": 1,
      "OV": 1,
      "UN": 0,
      "GG": 1,
      "NG": 0
    },
    "trasferta": {
      "PG": 3,
      "V": 0,
      "P": 1,
      "S": 2,
      "GF": 3,
      "GS": 8,
      "OV": 2,
      "UN": 1,
      "GG": 3,
      "NG": 0
    },
    "ultime5": {
      "PG": 4,
      "V": 1,
      "P": 1,
      "S": 2,
      "GF": 7,
      "GS": 9,
      "OV": 3,
      "UN": 1,
      "GG": 4,
      "NG": 0
    },
    "ultime5_casa": {
      "PG": 1,
      "V": 1,
      "P": 0,
      "S": 0,
      "GF": 4,
      "GS": 1,
      "OV": 1,
      "UN": 0,
      "GG": 1,
      "NG": 0
    },
    "ultime5_trasferta": {
      "PG": 3,
      "V": 0,
      "P": 1,
      "S": 2,
      "GF": 3,
      "GS": 8,
      "OV": 2,
      "UN": 1,
      "GG": 3,
      "NG": 0
    }
  }
]